onpod/__init__.py
onpod/models/settings.py
onpod/proxies/tensorflow_proxy.py
onpod/proxies/torch_proxy/__init__.py
onpod/proxies/torch_proxy/torch_proxy.py
onpod/proxies/transformers_proxy.py
onpod/proxy.py
onpod-0.0.31.dist-info/LICENSE
onpod-0.0.31.dist-info/METADATA
onpod-0.0.31.dist-info/WHEEL
onpod-0.0.31.dist-info/RECORD
