Metadata-Version: 2.1
Name: onpod
Version: 0.0.31
Summary: Runpod abstraction layer to behave as if using a local GPU
License: MIT
Author: gabewillen
Author-email: gabewillen@gmail.com
Requires-Python: >=3.11,<4.0
Classifier: License :: OSI Approved :: MIT License
Classifier: Programming Language :: Python :: 3
Classifier: Programming Language :: Python :: 3.11
Classifier: Programming Language :: Python :: 3.12
Requires-Dist: pydantic (>=2.9.1,<3.0.0)
Requires-Dist: pydantic-settings (>=2.5.0,<3.0.0)
Requires-Dist: runpod (>=1.7.0,<2.0.0)
Requires-Dist: torch (>=2.4.1,<3.0.0)
Requires-Dist: transformers (>=4.44.2,<5.0.0)
